{
  "school": "University of Tennessee, Knoxville",
  "base_url": "https://www.utsports.com",
  "season": "2026",
  "generated_at": "2026-03-21T07:48:39.579503Z",
  "record": "14-18",
  "most_recent_game": {
    "date": "2026-03-20",
    "opponent": "Missouri",
    "result": "L",
    "boxscore_url": "https://www.utsports.com/sports/baseball/stats/2026/missouri/boxscore/29732",
    "recap_url": "https://www.utsports.com/news/2026/3/20/baseball-21-22-vols-drop-sec-home-opener-to-missouri-8-4",
    "recap_headline": "University of Tennessee Athletics",
    "recap_text": "KNOXVILLE, Tenn. \u2013\nNo. 21/22 Tennessee lost its SEC home opener to Missouri, 8-4, on Friday night at Lindsey Nelson Stadium.\nThe Volunteers (15-7, 1-3 SEC) tried to battle back after digging themselves an early hole, but struggled to string together clutch hits, leaving 11 runners on base for the night.\nThe Tigers (16-6, 1-3 SEC) tagged UT starter\nTegan Kuhns\nfor three runs in the top of the third to jump out to a 3-0 lead before\nStone Lawless\ngot the Big Orange on the board with a solo home run in the bottom of the fourth inning.\nLawless was one of eight different Vols to record a hit on the night, finishing 2-for-4 after adding a double later in the game.\nA two-run RBI single by Blaize Ward capped a two-out rally and extended Missouri's lead to four in the top of the fifth, but Tennessee responded again in the bottom of the sixth with two runs of its own on a\nJay Abernathy\nRBI groundout and a\nTyler Myatt\npinch-hit RBI single to cut the deficit to 5-3.\nThe Tigers quickly ended UT's momentum, however, when Keegan Knutson crushed a three-run homer into the porches off of reliever\nBrandon Arvidson\nin the seventh inning to build their lead back up to five.\nAside from the homer, Arvidson pitched well, finishing with five strikeouts while pitching the final four innings for the Vols.\nBlaine Brown\nhit his seventh homer of the year to lead off the bottom of the seventh but that was the final time Tennessee would score on the night.\nUT didn't go down easily in the ninth, as it loaded the bases with walks from Brown,\nBlake Grimmer\nand\nReese Chapman\nbefore Mizzou reliever Sam Rosand came on to record the final out of the game and earn his second save of the season.\nUP NEXT:\nThe Vols will look to rebound and even the weekend series on Saturday night with first pitch slated for 6 p.m. on SEC Network+.",
    "watch_url": "https://www.espn.com/watch/player/_/id/e28f046d-4567-4e89-8583-f683815b6dbf"
  },
  "next_game": {
    "date": "2026-03-21",
    "opponent": "Missouri",
    "home_away": "home",
    "time_et": "6 PM ET",
    "watch_url": "https://www.espn.com/watch/player/_/id/23f11482-6845-4790-97a5-4a7e67329081"
  },
  "players": {
    "b0c1b4ca": {
      "id": "b0c1b4ca",
      "name": "Blaine Brown",
      "fn": "Blaine",
      "ln": "Brown",
      "pos": "OF/LHP",
      "yr": "So.",
      "num": "1",
      "school": "University of Tennessee, Knoxville",
      "season_batting": {
        "g": 22,
        "gs": 22,
        "avg": 0.293,
        "ops": 1.006,
        "ab": 82,
        "r": 19,
        "h": 24,
        "doubles": 7,
        "triples": 0,
        "hr": 7,
        "rbi": 20,
        "tb": 52,
        "slg": 0.634,
        "bb": 10,
        "hbp": 1,
        "so": 15,
        "gdp": 0,
        "obp": 0.372,
        "sf": 1,
        "sh": 0,
        "sb": 1,
        "sb_att": 1
      },
      "season_pitching": {
        "era": 4.5,
        "whip": 2.0,
        "w": 0,
        "l": 0,
        "sv": 0,
        "g": 3,
        "gs": 3,
        "ip": 2.0,
        "h": 1,
        "r": 1,
        "er": 1,
        "bb": 3,
        "so": 5,
        "hr": 0,
        "hbp": 1,
        "wp": 0,
        "opp_avg": ".143"
      },
      "last_game": {
        "date": "2026-03-20",
        "opponent": "Missouri",
        "result": "L",
        "boxscore_url": "https://www.utsports.com/sports/baseball/stats/2026/missouri/boxscore/29732",
        "batting": {
          "ab": 3,
          "r": 1,
          "h": 1,
          "rbi": 1,
          "bb": 2,
          "so": 0,
          "hr": 1,
          "doubles": 0,
          "triples": 0,
          "pos": ""
        },
        "pitching": {
          "ip": "1.0",
          "h": 1,
          "r": 0,
          "er": 0,
          "bb": 1,
          "so": 2,
          "wp": 0,
          "hbp": 0,
          "w": 0,
          "l": 0,
          "sv": 0
        }
      },
      "narrative": "1/3 with 1 RBI, 1 HR vs. Missouri (L). Hitting .292 with 7 HR through 22 games."
    },
    "ff6c0814": {
      "id": "ff6c0814",
      "name": "Ariel Antigua",
      "fn": "Ariel",
      "ln": "Antigua",
      "pos": "INF",
      "yr": "Jr.",
      "num": "2",
      "school": "University of Tennessee, Knoxville",
      "season_batting": {
        "g": 18,
        "gs": 12,
        "avg": 0.219,
        "ops": 0.747,
        "ab": 32,
        "r": 5,
        "h": 7,
        "doubles": 3,
        "triples": 0,
        "hr": 1,
        "rbi": 7,
        "tb": 13,
        "slg": 0.406,
        "bb": 5,
        "hbp": 2,
        "so": 4,
        "gdp": 2,
        "obp": 0.341,
        "sf": 2,
        "sh": 1,
        "sb": 1,
        "sb_att": 1
      },
      "season_pitching": null,
      "last_game": {
        "date": "2026-03-20",
        "opponent": "Missouri",
        "result": "L",
        "boxscore_url": "https://www.utsports.com/sports/baseball/stats/2026/missouri/boxscore/29732",
        "batting": {
          "ab": 2,
          "r": 0,
          "h": 0,
          "rbi": 0,
          "bb": 0,
          "so": 0,
          "hr": 0,
          "doubles": 0,
          "triples": 0,
          "pos": ""
        },
        "pitching": null
      },
      "narrative": "0/2 with 0 RBI vs. Missouri (L). Hitting .218 with 1 HR through 18 games."
    },
    "33676718": {
      "id": "33676718",
      "name": "Manny Marin",
      "fn": "Manny",
      "ln": "Marin",
      "pos": "INF",
      "yr": "So.",
      "num": "4",
      "school": "University of Tennessee, Knoxville",
      "season_batting": {
        "g": 18,
        "gs": 15,
        "avg": 0.362,
        "ops": 1.015,
        "ab": 58,
        "r": 9,
        "h": 21,
        "doubles": 4,
        "triples": 0,
        "hr": 4,
        "rbi": 14,
        "tb": 37,
        "slg": 0.638,
        "bb": 2,
        "hbp": 0,
        "so": 14,
        "gdp": 2,
        "obp": 0.377,
        "sf": 1,
        "sh": 1,
        "sb": 2,
        "sb_att": 2
      },
      "season_pitching": null,
      "last_game": {
        "date": "2026-03-20",
        "opponent": "Missouri",
        "result": "L",
        "boxscore_url": "https://www.utsports.com/sports/baseball/stats/2026/missouri/boxscore/29732",
        "batting": {
          "ab": 5,
          "r": 1,
          "h": 1,
          "rbi": 0,
          "bb": 0,
          "so": 1,
          "hr": 0,
          "doubles": 0,
          "triples": 0,
          "pos": ""
        },
        "pitching": null
      },
      "narrative": "1/5 with 0 RBI vs. Missouri (L). Hitting .362 with 4 HR through 18 games."
    },
    "5f00d08b": {
      "id": "5f00d08b",
      "name": "Garrett Wright",
      "fn": "Garrett",
      "ln": "Wright",
      "pos": "C/OF",
      "yr": "Jr.",
      "num": "5",
      "school": "University of Tennessee, Knoxville",
      "season_batting": {
        "g": 11,
        "gs": 10,
        "avg": 0.314,
        "ops": 0.956,
        "ab": 35,
        "r": 8,
        "h": 11,
        "doubles": 4,
        "triples": 0,
        "hr": 1,
        "rbi": 3,
        "tb": 18,
        "slg": 0.514,
        "bb": 1,
        "hbp": 7,
        "so": 6,
        "gdp": 0,
        "obp": 0.442,
        "sf": 0,
        "sh": 0,
        "sb": 0,
        "sb_att": 0
      },
      "season_pitching": null,
      "last_game": {
        "date": "2026-03-20",
        "opponent": "Missouri",
        "result": "L",
        "boxscore_url": "https://www.utsports.com/sports/baseball/stats/2026/missouri/boxscore/29732",
        "batting": {
          "ab": 5,
          "r": 0,
          "h": 1,
          "rbi": 0,
          "bb": 0,
          "so": 1,
          "hr": 0,
          "doubles": 0,
          "triples": 0,
          "pos": ""
        },
        "pitching": null
      },
      "narrative": "1/5 with 0 RBI vs. Missouri (L). Hitting .314 with 1 HR through 11 games."
    },
    "897eef84": {
      "id": "897eef84",
      "name": "Brady Frederick",
      "fn": "Brady",
      "ln": "Frederick",
      "pos": "RHP",
      "yr": "Jr.",
      "num": "6",
      "school": "University of Tennessee, Knoxville",
      "season_batting": null,
      "season_pitching": {
        "era": 3.78,
        "whip": 1.08,
        "w": 4,
        "l": 0,
        "sv": 0,
        "g": 11,
        "gs": 0,
        "ip": 16.2,
        "h": 14,
        "r": 8,
        "er": 7,
        "bb": 4,
        "so": 18,
        "hr": 1,
        "hbp": 2,
        "wp": 0,
        "opp_avg": ".241"
      },
      "last_game": {
        "date": "2026-03-20",
        "opponent": "Missouri",
        "result": "L",
        "boxscore_url": "https://www.utsports.com/sports/baseball/stats/2026/missouri/boxscore/29732",
        "batting": null,
        "pitching": {
          "ip": "2.0",
          "h": 3,
          "r": 2,
          "er": 2,
          "bb": 0,
          "so": 1,
          "wp": 0,
          "hbp": 1,
          "w": 0,
          "l": 0,
          "sv": 0
        }
      },
      "narrative": "2.0 IP, 1 K vs. Missouri (L). At 3.89 ERA through 16.2 innings on the season."
    },
    "5934dff3": {
      "id": "5934dff3",
      "name": "Mark Hindy",
      "fn": "Mark",
      "ln": "Hindy",
      "pos": "LHP",
      "yr": "Gr.",
      "num": "7",
      "school": "University of Tennessee, Knoxville",
      "season_batting": null,
      "season_pitching": {
        "era": 4.5,
        "whip": 0.83,
        "w": 1,
        "l": 0,
        "sv": 0,
        "g": 7,
        "gs": 0,
        "ip": 6.0,
        "h": 4,
        "r": 3,
        "er": 3,
        "bb": 1,
        "so": 5,
        "hr": 1,
        "hbp": 2,
        "wp": 0,
        "opp_avg": ".182"
      },
      "last_game": {
        "date": "2026-03-17",
        "opponent": "Eastern Kentucky",
        "result": "W",
        "boxscore_url": "https://www.utsports.com/sports/baseball/stats/2026/eastern-kentucky/boxscore/29940",
        "batting": null,
        "pitching": {
          "ip": "1.0",
          "h": 1,
          "r": 1,
          "er": 1,
          "bb": 0,
          "so": 1,
          "wp": 0,
          "hbp": 1,
          "w": 0,
          "l": 0,
          "sv": 0
        }
      },
      "narrative": "1.0 IP, 1 K vs. Eastern Kentucky (W). At 4.50 ERA through 6.0 innings on the season."
    },
    "a0caa771": {
      "id": "a0caa771",
      "name": "Jay Abernathy",
      "fn": "Jay",
      "ln": "Abernathy",
      "pos": "OF/INF",
      "yr": "So.",
      "num": "8",
      "school": "University of Tennessee, Knoxville",
      "season_batting": {
        "g": 22,
        "gs": 22,
        "avg": 0.24,
        "ops": 0.747,
        "ab": 75,
        "r": 18,
        "h": 18,
        "doubles": 5,
        "triples": 1,
        "hr": 1,
        "rbi": 8,
        "tb": 28,
        "slg": 0.373,
        "bb": 15,
        "hbp": 1,
        "so": 21,
        "gdp": 1,
        "obp": 0.374,
        "sf": 0,
        "sh": 0,
        "sb": 3,
        "sb_att": 4
      },
      "season_pitching": null,
      "last_game": {
        "date": "2026-03-20",
        "opponent": "Missouri",
        "result": "L",
        "boxscore_url": "https://www.utsports.com/sports/baseball/stats/2026/missouri/boxscore/29732",
        "batting": {
          "ab": 4,
          "r": 0,
          "h": 0,
          "rbi": 1,
          "bb": 0,
          "so": 1,
          "hr": 0,
          "doubles": 0,
          "triples": 0,
          "pos": ""
        },
        "pitching": null
      },
      "narrative": "0/4 with 1 RBI vs. Missouri (L). Hitting .240 with 1 HR through 22 games."
    },
    "6e8c8fd5": {
      "id": "6e8c8fd5",
      "name": "Henry Ford",
      "fn": "Henry",
      "ln": "Ford",
      "pos": "INF/OF",
      "yr": "Jr.",
      "num": "9",
      "school": "University of Tennessee, Knoxville",
      "season_batting": {
        "g": 21,
        "gs": 21,
        "avg": 0.348,
        "ops": 1.065,
        "ab": 89,
        "r": 19,
        "h": 31,
        "doubles": 4,
        "triples": 0,
        "hr": 8,
        "rbi": 25,
        "tb": 59,
        "slg": 0.663,
        "bb": 8,
        "hbp": 0,
        "so": 10,
        "gdp": 1,
        "obp": 0.402,
        "sf": 0,
        "sh": 0,
        "sb": 3,
        "sb_att": 4
      },
      "season_pitching": null,
      "last_game": {
        "date": "2026-03-20",
        "opponent": "Missouri",
        "result": "L",
        "boxscore_url": "https://www.utsports.com/sports/baseball/stats/2026/missouri/boxscore/29732",
        "batting": {
          "ab": 4,
          "r": 0,
          "h": 1,
          "rbi": 0,
          "bb": 1,
          "so": 1,
          "hr": 0,
          "doubles": 0,
          "triples": 0,
          "pos": ""
        },
        "pitching": null
      },
      "narrative": "1/4 with 0 RBI vs. Missouri (L). Hitting .348 with 8 HR through 21 games."
    },
    "fac562ba": {
      "id": "fac562ba",
      "name": "Evan Blanco",
      "fn": "Evan",
      "ln": "Blanco",
      "pos": "LHP",
      "yr": "Sr.",
      "num": "11",
      "school": "University of Tennessee, Knoxville",
      "season_batting": null,
      "season_pitching": {
        "era": 3.2,
        "whip": 1.11,
        "w": 1,
        "l": 2,
        "sv": 0,
        "g": 5,
        "gs": 5,
        "ip": 25.1,
        "h": 15,
        "r": 10,
        "er": 9,
        "bb": 13,
        "so": 39,
        "hr": 2,
        "hbp": 5,
        "wp": 0,
        "opp_avg": ".169"
      },
      "last_game": {
        "date": "2026-03-15",
        "opponent": "Georgia",
        "result": "L",
        "boxscore_url": "https://www.utsports.com/sports/baseball/stats/2026/georgia/boxscore/29731",
        "batting": null,
        "pitching": {
          "ip": "5.2",
          "h": 3,
          "r": 3,
          "er": 3,
          "bb": 3,
          "so": 8,
          "wp": 0,
          "hbp": 1,
          "w": 0,
          "l": 0,
          "sv": 0
        }
      },
      "narrative": "Took the mound against Georgia, throwing 5.2 innings. Struck out 8 while allowing just 3 hit(s) and 3 earned run(s) in a quality start."
    },
    "313c6d44": {
      "id": "313c6d44",
      "name": "Evan Hankins",
      "fn": "Evan",
      "ln": "Hankins",
      "pos": "INF",
      "yr": "Fr.",
      "num": "12",
      "school": "University of Tennessee, Knoxville",
      "season_batting": {
        "g": 5,
        "gs": 1,
        "avg": 0.0,
        "ops": 0.143,
        "ab": 6,
        "r": 1,
        "h": 0,
        "doubles": 0,
        "triples": 0,
        "hr": 0,
        "rbi": 0,
        "tb": 0,
        "slg": 0.0,
        "bb": 1,
        "hbp": 0,
        "so": 3,
        "gdp": 0,
        "obp": 0.143,
        "sf": 0,
        "sh": 0,
        "sb": 0,
        "sb_att": 0
      },
      "season_pitching": null,
      "last_game": {
        "date": "2026-03-10",
        "opponent": "Tennessee Tech",
        "result": "W",
        "boxscore_url": "https://www.utsports.com/sports/baseball/stats/2026/tennessee-tech/boxscore/29939",
        "batting": {
          "ab": 1,
          "r": 0,
          "h": 0,
          "rbi": 0,
          "bb": 0,
          "so": 0,
          "hr": 0,
          "doubles": 0,
          "triples": 0,
          "pos": ""
        },
        "pitching": null
      },
      "narrative": "Went 0/1 with 0 RBI against Tennessee Tech. Struggled to make contact."
    },
    "d6b74cc8": {
      "id": "d6b74cc8",
      "name": "Reese Chapman",
      "fn": "Reese",
      "ln": "Chapman",
      "pos": "OF",
      "yr": "Sr.",
      "num": "13",
      "school": "University of Tennessee, Knoxville",
      "season_batting": {
        "g": 21,
        "gs": 21,
        "avg": 0.318,
        "ops": 0.989,
        "ab": 66,
        "r": 19,
        "h": 21,
        "doubles": 9,
        "triples": 0,
        "hr": 2,
        "rbi": 15,
        "tb": 36,
        "slg": 0.545,
        "bb": 15,
        "hbp": 0,
        "so": 15,
        "gdp": 1,
        "obp": 0.444,
        "sf": 0,
        "sh": 0,
        "sb": 2,
        "sb_att": 2
      },
      "season_pitching": null,
      "last_game": {
        "date": "2026-03-20",
        "opponent": "Missouri",
        "result": "L",
        "boxscore_url": "https://www.utsports.com/sports/baseball/stats/2026/missouri/boxscore/29732",
        "batting": {
          "ab": 4,
          "r": 1,
          "h": 1,
          "rbi": 0,
          "bb": 1,
          "so": 1,
          "hr": 0,
          "doubles": 1,
          "triples": 0,
          "pos": ""
        },
        "pitching": null
      },
      "narrative": "1/4 with 0 RBI vs. Missouri (L). Hitting .318 with 2 HR through 21 games."
    },
    "0ab28757": {
      "id": "0ab28757",
      "name": "Blake Grimmer",
      "fn": "Blake",
      "ln": "Grimmer",
      "pos": "UTL",
      "yr": "So.",
      "num": "14",
      "school": "University of Tennessee, Knoxville",
      "season_batting": {
        "g": 10,
        "gs": 10,
        "avg": 0.303,
        "ops": 1.028,
        "ab": 33,
        "r": 8,
        "h": 10,
        "doubles": 3,
        "triples": 0,
        "hr": 2,
        "rbi": 4,
        "tb": 19,
        "slg": 0.576,
        "bb": 9,
        "hbp": 0,
        "so": 9,
        "gdp": 1,
        "obp": 0.452,
        "sf": 0,
        "sh": 0,
        "sb": 1,
        "sb_att": 1
      },
      "season_pitching": null,
      "last_game": {
        "date": "2026-03-20",
        "opponent": "Missouri",
        "result": "L",
        "boxscore_url": "https://www.utsports.com/sports/baseball/stats/2026/missouri/boxscore/29732",
        "batting": {
          "ab": 3,
          "r": 0,
          "h": 1,
          "rbi": 0,
          "bb": 2,
          "so": 1,
          "hr": 0,
          "doubles": 0,
          "triples": 0,
          "pos": ""
        },
        "pitching": null
      },
      "narrative": "1/3 with 0 RBI vs. Missouri (L). Hitting .303 with 2 HR through 10 games."
    },
    "95952ad2": {
      "id": "95952ad2",
      "name": "Hunter High",
      "fn": "Hunter",
      "ln": "High",
      "pos": "OF/INF",
      "yr": "Jr.",
      "num": "15",
      "school": "University of Tennessee, Knoxville",
      "season_batting": {
        "g": 6,
        "gs": 1,
        "avg": 0.143,
        "ops": 0.365,
        "ab": 7,
        "r": 2,
        "h": 1,
        "doubles": 0,
        "triples": 0,
        "hr": 0,
        "rbi": 1,
        "tb": 1,
        "slg": 0.143,
        "bb": 1,
        "hbp": 0,
        "so": 0,
        "gdp": 1,
        "obp": 0.222,
        "sf": 1,
        "sh": 0,
        "sb": 0,
        "sb_att": 0
      },
      "season_pitching": null,
      "last_game": {
        "date": "2026-03-10",
        "opponent": "Tennessee Tech",
        "result": "W",
        "boxscore_url": "https://www.utsports.com/sports/baseball/stats/2026/tennessee-tech/boxscore/29939",
        "batting": {
          "ab": 2,
          "r": 1,
          "h": 1,
          "rbi": 0,
          "bb": 0,
          "so": 0,
          "hr": 0,
          "doubles": 0,
          "triples": 0,
          "pos": ""
        },
        "pitching": null
      },
      "narrative": "Went 1/2 with 0 RBI against Tennessee Tech. Had an outstanding performance at the plate (0.500)."
    },
    "eb0528d6": {
      "id": "eb0528d6",
      "name": "Levi Clark",
      "fn": "Levi",
      "ln": "Clark",
      "pos": "UTL",
      "yr": "So.",
      "num": "16",
      "school": "University of Tennessee, Knoxville",
      "season_batting": {
        "g": 17,
        "gs": 16,
        "avg": 0.172,
        "ops": 0.612,
        "ab": 58,
        "r": 8,
        "h": 10,
        "doubles": 4,
        "triples": 0,
        "hr": 1,
        "rbi": 9,
        "tb": 17,
        "slg": 0.293,
        "bb": 9,
        "hbp": 4,
        "so": 10,
        "gdp": 0,
        "obp": 0.319,
        "sf": 1,
        "sh": 0,
        "sb": 0,
        "sb_att": 0
      },
      "season_pitching": null,
      "last_game": {
        "date": "2026-03-17",
        "opponent": "Eastern Kentucky",
        "result": "W",
        "boxscore_url": "https://www.utsports.com/sports/baseball/stats/2026/eastern-kentucky/boxscore/29940",
        "batting": {
          "ab": 3,
          "r": 1,
          "h": 1,
          "rbi": 2,
          "bb": 1,
          "so": 0,
          "hr": 0,
          "doubles": 0,
          "triples": 0,
          "pos": ""
        },
        "pitching": null
      },
      "narrative": "1/3 with 2 RBI vs. Eastern Kentucky (W). Hitting .172 with 1 HR through 17 games."
    },
    "4df6aafa": {
      "id": "4df6aafa",
      "name": "Nate Eisfelder",
      "fn": "Nate",
      "ln": "Eisfelder",
      "pos": "OF",
      "yr": "Fr.",
      "num": "17",
      "school": "University of Tennessee, Knoxville",
      "season_batting": {
        "g": 7,
        "gs": 0,
        "avg": 0.2,
        "ops": 1.229,
        "ab": 5,
        "r": 1,
        "h": 1,
        "doubles": 0,
        "triples": 0,
        "hr": 1,
        "rbi": 5,
        "tb": 4,
        "slg": 0.8,
        "bb": 2,
        "hbp": 0,
        "so": 2,
        "gdp": 0,
        "obp": 0.429,
        "sf": 0,
        "sh": 0,
        "sb": 0,
        "sb_att": 0
      },
      "season_pitching": null,
      "last_game": {
        "date": "2026-03-10",
        "opponent": "Tennessee Tech",
        "result": "W",
        "boxscore_url": "https://www.utsports.com/sports/baseball/stats/2026/tennessee-tech/boxscore/29939",
        "batting": {
          "ab": 2,
          "r": 1,
          "h": 1,
          "rbi": 4,
          "bb": 0,
          "so": 0,
          "hr": 1,
          "doubles": 0,
          "triples": 0,
          "pos": ""
        },
        "pitching": null
      },
      "narrative": "Went 1/2 with 4 RBI against Tennessee Tech. Hit 1 home run(s). Had an outstanding performance at the plate (0.500)."
    },
    "c537122e": {
      "id": "c537122e",
      "name": "Landon Mack",
      "fn": "Landon",
      "ln": "Mack",
      "pos": "RHP",
      "yr": "So.",
      "num": "18",
      "school": "University of Tennessee, Knoxville",
      "season_batting": null,
      "season_pitching": {
        "era": 3.21,
        "whip": 1.43,
        "w": 3,
        "l": 2,
        "sv": 0,
        "g": 5,
        "gs": 5,
        "ip": 28.0,
        "h": 27,
        "r": 11,
        "er": 10,
        "bb": 13,
        "so": 34,
        "hr": 3,
        "hbp": 1,
        "wp": 0,
        "opp_avg": ".260"
      },
      "last_game": {
        "date": "2026-03-14",
        "opponent": "Georgia",
        "result": "L",
        "boxscore_url": "https://www.utsports.com/sports/baseball/stats/2026/georgia/boxscore/29730",
        "batting": null,
        "pitching": {
          "ip": "5.1",
          "h": 9,
          "r": 4,
          "er": 4,
          "bb": 4,
          "so": 4,
          "wp": 0,
          "hbp": 0,
          "w": 0,
          "l": 1,
          "sv": 0
        }
      },
      "narrative": "Took the mound against Georgia, throwing 5.1 innings. Struck out 4 while allowing just 9 hit(s) and 4 earned run(s) in a quality start."
    },
    "46e6f9de": {
      "id": "46e6f9de",
      "name": "Cam Appenzeller",
      "fn": "Cam",
      "ln": "Appenzeller",
      "pos": "LHP",
      "yr": "Fr.",
      "num": "19",
      "school": "University of Tennessee, Knoxville",
      "season_batting": null,
      "season_pitching": {
        "era": 2.3,
        "whip": 0.83,
        "w": 2,
        "l": 0,
        "sv": 1,
        "g": 7,
        "gs": 0,
        "ip": 15.2,
        "h": 10,
        "r": 4,
        "er": 4,
        "bb": 3,
        "so": 18,
        "hr": 0,
        "hbp": 0,
        "wp": 0,
        "opp_avg": ".189"
      },
      "last_game": {
        "date": "2026-03-14",
        "opponent": "Georgia",
        "result": "L",
        "boxscore_url": "https://www.utsports.com/sports/baseball/stats/2026/georgia/boxscore/29730",
        "batting": null,
        "pitching": {
          "ip": "2.2",
          "h": 2,
          "r": 0,
          "er": 0,
          "bb": 0,
          "so": 2,
          "wp": 0,
          "hbp": 0,
          "w": 0,
          "l": 0,
          "sv": 0
        }
      },
      "narrative": "Took the mound against Georgia, throwing 2.2 innings. Allowed 0 earned run(s) with 2 strikeout(s)."
    },
    "4421dc5f": {
      "id": "4421dc5f",
      "name": "Tyler Myatt",
      "fn": "Tyler",
      "ln": "Myatt",
      "pos": "INF/OF",
      "yr": "So.",
      "num": "20",
      "school": "University of Tennessee, Knoxville",
      "season_batting": {
        "g": 19,
        "gs": 12,
        "avg": 0.224,
        "ops": 0.774,
        "ab": 49,
        "r": 7,
        "h": 11,
        "doubles": 4,
        "triples": 0,
        "hr": 2,
        "rbi": 9,
        "tb": 21,
        "slg": 0.429,
        "bb": 6,
        "hbp": 3,
        "so": 19,
        "gdp": 1,
        "obp": 0.345,
        "sf": 0,
        "sh": 0,
        "sb": 0,
        "sb_att": 0
      },
      "season_pitching": null,
      "last_game": {
        "date": "2026-03-20",
        "opponent": "Missouri",
        "result": "L",
        "boxscore_url": "https://www.utsports.com/sports/baseball/stats/2026/missouri/boxscore/29732",
        "batting": {
          "ab": 2,
          "r": 0,
          "h": 1,
          "rbi": 1,
          "bb": 0,
          "so": 1,
          "hr": 0,
          "doubles": 0,
          "triples": 0,
          "pos": ""
        },
        "pitching": null
      },
      "narrative": "1/2 with 1 RBI vs. Missouri (L). Hitting .224 with 2 HR through 19 games."
    },
    "46d5d1a4": {
      "id": "46d5d1a4",
      "name": "Tegan Kuhns",
      "fn": "Tegan",
      "ln": "Kuhns",
      "pos": "RHP",
      "yr": "So.",
      "num": "21",
      "school": "University of Tennessee, Knoxville",
      "season_batting": null,
      "season_pitching": {
        "era": 4.35,
        "whip": 1.1,
        "w": 1,
        "l": 2,
        "sv": 0,
        "g": 6,
        "gs": 6,
        "ip": 31.0,
        "h": 29,
        "r": 17,
        "er": 15,
        "bb": 5,
        "so": 40,
        "hr": 6,
        "hbp": 3,
        "wp": 1,
        "opp_avg": ".240"
      },
      "last_game": {
        "date": "2026-03-20",
        "opponent": "Missouri",
        "result": "L",
        "boxscore_url": "https://www.utsports.com/sports/baseball/stats/2026/missouri/boxscore/29732",
        "batting": null,
        "pitching": {
          "ip": "3.0",
          "h": 6,
          "r": 3,
          "er": 3,
          "bb": 1,
          "so": 5,
          "wp": 0,
          "hbp": 0,
          "w": 0,
          "l": 1,
          "sv": 0
        }
      },
      "narrative": "3.0 IP, 5 K vs. Missouri (L). At 4.35 ERA through 31.0 innings on the season."
    },
    "4c80f46b": {
      "id": "4c80f46b",
      "name": "Brandon Arvidson",
      "fn": "Brandon",
      "ln": "Arvidson",
      "pos": "LHP",
      "yr": "Jr.",
      "num": "25",
      "school": "University of Tennessee, Knoxville",
      "season_batting": null,
      "season_pitching": {
        "era": 3.52,
        "whip": 1.11,
        "w": 1,
        "l": 0,
        "sv": 0,
        "g": 6,
        "gs": 0,
        "ip": 15.1,
        "h": 12,
        "r": 6,
        "er": 6,
        "bb": 5,
        "so": 21,
        "hr": 2,
        "hbp": 1,
        "wp": 2,
        "opp_avg": ".218"
      },
      "last_game": {
        "date": "2026-03-13",
        "opponent": "Georgia",
        "result": "W",
        "boxscore_url": "https://www.utsports.com/sports/baseball/stats/2026/georgia/boxscore/29729",
        "batting": null,
        "pitching": {
          "ip": "4.1",
          "h": 2,
          "r": 0,
          "er": 0,
          "bb": 2,
          "so": 4,
          "wp": 0,
          "hbp": 0,
          "w": 1,
          "l": 0,
          "sv": 0
        }
      },
      "narrative": "Took the mound against Georgia, throwing 4.1 innings. Allowed 0 earned run(s) with 4 strikeout(s)."
    },
    "3e6b8de3": {
      "id": "3e6b8de3",
      "name": "Chris Newstrom",
      "fn": "Chris",
      "ln": "Newstrom",
      "pos": "INF/OF",
      "yr": "So.",
      "num": "26",
      "school": "University of Tennessee, Knoxville",
      "season_batting": {
        "g": 16,
        "gs": 14,
        "avg": 0.196,
        "ops": 0.644,
        "ab": 46,
        "r": 8,
        "h": 9,
        "doubles": 2,
        "triples": 1,
        "hr": 1,
        "rbi": 6,
        "tb": 16,
        "slg": 0.348,
        "bb": 6,
        "hbp": 1,
        "so": 12,
        "gdp": 0,
        "obp": 0.296,
        "sf": 1,
        "sh": 0,
        "sb": 0,
        "sb_att": 0
      },
      "season_pitching": null,
      "last_game": {
        "date": "2026-03-15",
        "opponent": "Georgia",
        "result": "L",
        "boxscore_url": "https://www.utsports.com/sports/baseball/stats/2026/georgia/boxscore/29731",
        "batting": {
          "ab": 2,
          "r": 0,
          "h": 0,
          "rbi": 0,
          "bb": 0,
          "so": 2,
          "hr": 0,
          "doubles": 0,
          "triples": 0,
          "pos": ""
        },
        "pitching": null
      },
      "narrative": "Went 0/2 with 0 RBI against Georgia. Struggled to make contact."
    },
    "98592e16": {
      "id": "98592e16",
      "name": "Stone Lawless",
      "fn": "Stone",
      "ln": "Lawless",
      "pos": "C",
      "yr": "So.",
      "num": "27",
      "school": "University of Tennessee, Knoxville",
      "season_batting": {
        "g": 16,
        "gs": 15,
        "avg": 0.26,
        "ops": 0.943,
        "ab": 50,
        "r": 7,
        "h": 13,
        "doubles": 2,
        "triples": 0,
        "hr": 4,
        "rbi": 9,
        "tb": 27,
        "slg": 0.54,
        "bb": 8,
        "hbp": 4,
        "so": 10,
        "gdp": 2,
        "obp": 0.403,
        "sf": 0,
        "sh": 0,
        "sb": 1,
        "sb_att": 1
      },
      "season_pitching": null,
      "last_game": {
        "date": "2026-03-20",
        "opponent": "Missouri",
        "result": "L",
        "boxscore_url": "https://www.utsports.com/sports/baseball/stats/2026/missouri/boxscore/29732",
        "batting": {
          "ab": 4,
          "r": 1,
          "h": 2,
          "rbi": 1,
          "bb": 0,
          "so": 1,
          "hr": 1,
          "doubles": 1,
          "triples": 0,
          "pos": ""
        },
        "pitching": null
      },
      "narrative": "2/4 with 1 RBI, 1 HR vs. Missouri (L). Hitting .260 with 4 HR through 16 games."
    },
    "10be9d62": {
      "id": "10be9d62",
      "name": "Taylor Tracey",
      "fn": "Taylor",
      "ln": "Tracey",
      "pos": "LHP/OF",
      "yr": "Fr.",
      "num": "29",
      "school": "University of Tennessee, Knoxville",
      "season_batting": {
        "g": 6,
        "gs": 3,
        "avg": 0.0,
        "ops": 0.0,
        "ab": 2,
        "r": 0,
        "h": 0,
        "doubles": 0,
        "triples": 0,
        "hr": 0,
        "rbi": 0,
        "tb": 0,
        "slg": 0.0,
        "bb": 0,
        "hbp": 0,
        "so": 1,
        "gdp": 0,
        "obp": 0.0,
        "sf": 0,
        "sh": 0,
        "sb": 0,
        "sb_att": 0
      },
      "season_pitching": {
        "era": 1.54,
        "whip": 0.77,
        "w": 0,
        "l": 0,
        "sv": 0,
        "g": 6,
        "gs": 3,
        "ip": 11.2,
        "h": 6,
        "r": 2,
        "er": 2,
        "bb": 3,
        "so": 19,
        "hr": 1,
        "hbp": 3,
        "wp": 0,
        "opp_avg": ".146"
      },
      "last_game": {
        "date": "2026-03-17",
        "opponent": "Eastern Kentucky",
        "result": "W",
        "boxscore_url": "https://www.utsports.com/sports/baseball/stats/2026/eastern-kentucky/boxscore/29940",
        "batting": {
          "ab": 2,
          "r": 0,
          "h": 0,
          "rbi": 0,
          "bb": 0,
          "so": 1,
          "hr": 0,
          "doubles": 0,
          "triples": 0,
          "pos": ""
        },
        "pitching": {
          "ip": "2.1",
          "h": 1,
          "r": 0,
          "er": 0,
          "bb": 0,
          "so": 4,
          "wp": 0,
          "hbp": 3,
          "w": 0,
          "l": 0,
          "sv": 0
        }
      },
      "narrative": "0/2 with 0 RBI vs. Eastern Kentucky (W). Hitting .000 with 0 HR through 6 games."
    },
    "7effe319": {
      "id": "7effe319",
      "name": "Trent Grindlinger",
      "fn": "Trent",
      "ln": "Grindlinger",
      "pos": "C",
      "yr": "Fr.",
      "num": "30",
      "school": "University of Tennessee, Knoxville",
      "season_batting": {
        "g": 8,
        "gs": 3,
        "avg": 0.533,
        "ops": 1.296,
        "ab": 15,
        "r": 3,
        "h": 8,
        "doubles": 1,
        "triples": 1,
        "hr": 0,
        "rbi": 3,
        "tb": 11,
        "slg": 0.733,
        "bb": 0,
        "hbp": 1,
        "so": 2,
        "gdp": 0,
        "obp": 0.563,
        "sf": 0,
        "sh": 0,
        "sb": 0,
        "sb_att": 1
      },
      "season_pitching": null,
      "last_game": {
        "date": "2026-03-17",
        "opponent": "Eastern Kentucky",
        "result": "W",
        "boxscore_url": "https://www.utsports.com/sports/baseball/stats/2026/eastern-kentucky/boxscore/29940",
        "batting": {
          "ab": 3,
          "r": 2,
          "h": 3,
          "rbi": 2,
          "bb": 0,
          "so": 0,
          "hr": 0,
          "doubles": 0,
          "triples": 1,
          "pos": ""
        },
        "pitching": null
      },
      "narrative": "3/3 with 2 RBI vs. Eastern Kentucky (W). Hitting .533 with 0 HR through 8 games."
    },
    "26b3b032": {
      "id": "26b3b032",
      "name": "Finley Bates",
      "fn": "Finley",
      "ln": "Bates",
      "pos": "INF",
      "yr": "Jr.",
      "num": "31",
      "school": "University of Tennessee, Knoxville",
      "season_batting": {
        "g": 8,
        "gs": 2,
        "avg": 0.5,
        "ops": 1.475,
        "ab": 8,
        "r": 3,
        "h": 4,
        "doubles": 0,
        "triples": 0,
        "hr": 1,
        "rbi": 1,
        "tb": 7,
        "slg": 0.875,
        "bb": 0,
        "hbp": 2,
        "so": 1,
        "gdp": 0,
        "obp": 0.6,
        "sf": 0,
        "sh": 0,
        "sb": 0,
        "sb_att": 1
      },
      "season_pitching": null,
      "last_game": {
        "date": "2026-02-24",
        "opponent": "Bellarmine",
        "result": "W",
        "boxscore_url": "https://www.utsports.com/sports/baseball/stats/2026/bellarmine/boxscore/29933",
        "batting": {
          "ab": 2,
          "r": 0,
          "h": 1,
          "rbi": 0,
          "bb": 0,
          "so": 0,
          "hr": 0,
          "doubles": 0,
          "triples": 0,
          "pos": ""
        },
        "pitching": null
      },
      "narrative": "Went 1/2 with 0 RBI against Bellarmine. Had an outstanding performance at the plate (0.500)."
    },
    "29d528dd": {
      "id": "29d528dd",
      "name": "Bo Rhudy",
      "fn": "Bo",
      "ln": "Rhudy",
      "pos": "RHP",
      "yr": "Jr.",
      "num": "33",
      "school": "University of Tennessee, Knoxville",
      "season_batting": null,
      "season_pitching": {
        "era": 1.23,
        "whip": 0.68,
        "w": 0,
        "l": 0,
        "sv": 0,
        "g": 7,
        "gs": 0,
        "ip": 7.1,
        "h": 5,
        "r": 1,
        "er": 1,
        "bb": 0,
        "so": 12,
        "hr": 0,
        "hbp": 2,
        "wp": 0,
        "opp_avg": ".185"
      },
      "last_game": {
        "date": "2026-03-17",
        "opponent": "Eastern Kentucky",
        "result": "W",
        "boxscore_url": "https://www.utsports.com/sports/baseball/stats/2026/eastern-kentucky/boxscore/29940",
        "batting": null,
        "pitching": {
          "ip": "0.1",
          "h": 0,
          "r": 0,
          "er": 0,
          "bb": 0,
          "so": 1,
          "wp": 0,
          "hbp": 0,
          "w": 0,
          "l": 0,
          "sv": 0
        }
      },
      "narrative": "0.1 IP, 1 K vs. Eastern Kentucky (W). At 1.27 ERA through 7.1 innings on the season."
    },
    "d9bb80cf": {
      "id": "d9bb80cf",
      "name": "Brayden Krenzel",
      "fn": "Brayden",
      "ln": "Krenzel",
      "pos": "RHP",
      "yr": "So.",
      "num": "34",
      "school": "University of Tennessee, Knoxville",
      "season_batting": null,
      "season_pitching": {
        "era": 7.0,
        "whip": 1.33,
        "w": 0,
        "l": 1,
        "sv": 2,
        "g": 7,
        "gs": 0,
        "ip": 9.0,
        "h": 7,
        "r": 8,
        "er": 7,
        "bb": 5,
        "so": 17,
        "hr": 1,
        "hbp": 3,
        "wp": 2,
        "opp_avg": ".206"
      },
      "last_game": {
        "date": "2026-03-17",
        "opponent": "Eastern Kentucky",
        "result": "W",
        "boxscore_url": "https://www.utsports.com/sports/baseball/stats/2026/eastern-kentucky/boxscore/29940",
        "batting": null,
        "pitching": {
          "ip": "0.1",
          "h": 0,
          "r": 1,
          "er": 0,
          "bb": 1,
          "so": 1,
          "wp": 0,
          "hbp": 1,
          "w": 0,
          "l": 0,
          "sv": 0
        }
      },
      "narrative": "0.1 IP, 1 K vs. Eastern Kentucky (W). At 7.00 ERA through 9.0 innings on the season."
    },
    "2cf7fa34": {
      "id": "2cf7fa34",
      "name": "Sawyer Deering",
      "fn": "Sawyer",
      "ln": "Deering",
      "pos": "RHP",
      "yr": "Fr.",
      "num": "36",
      "school": "University of Tennessee, Knoxville",
      "season_batting": null,
      "season_pitching": {
        "era": 2.25,
        "whip": 1.0,
        "w": 0,
        "l": 0,
        "sv": 0,
        "g": 5,
        "gs": 0,
        "ip": 4.0,
        "h": 1,
        "r": 2,
        "er": 1,
        "bb": 3,
        "so": 4,
        "hr": 0,
        "hbp": 1,
        "wp": 0,
        "opp_avg": ".077"
      },
      "last_game": {
        "date": "2026-03-17",
        "opponent": "Eastern Kentucky",
        "result": "W",
        "boxscore_url": "https://www.utsports.com/sports/baseball/stats/2026/eastern-kentucky/boxscore/29940",
        "batting": null,
        "pitching": {
          "ip": "1.1",
          "h": 0,
          "r": 0,
          "er": 0,
          "bb": 0,
          "so": 2,
          "wp": 0,
          "hbp": 0,
          "w": 0,
          "l": 0,
          "sv": 0
        }
      },
      "narrative": "1.1 IP, 2 K vs. Eastern Kentucky (W). At 2.25 ERA through 4.0 innings on the season."
    },
    "7a7b2263": {
      "id": "7a7b2263",
      "name": "Ethan Baiotto",
      "fn": "Ethan",
      "ln": "Baiotto",
      "pos": "RHP",
      "yr": "Fr.",
      "num": "38",
      "school": "University of Tennessee, Knoxville",
      "season_batting": null,
      "season_pitching": {
        "era": 7.2,
        "whip": 1.8,
        "w": 1,
        "l": 0,
        "sv": 0,
        "g": 5,
        "gs": 0,
        "ip": 5.0,
        "h": 6,
        "r": 4,
        "er": 4,
        "bb": 3,
        "so": 4,
        "hr": 0,
        "hbp": 2,
        "wp": 0,
        "opp_avg": ".286"
      },
      "last_game": {
        "date": "2026-03-17",
        "opponent": "Eastern Kentucky",
        "result": "W",
        "boxscore_url": "https://www.utsports.com/sports/baseball/stats/2026/eastern-kentucky/boxscore/29940",
        "batting": null,
        "pitching": {
          "ip": "1.1",
          "h": 4,
          "r": 1,
          "er": 1,
          "bb": 0,
          "so": 0,
          "wp": 0,
          "hbp": 0,
          "w": 0,
          "l": 0,
          "sv": 0
        }
      },
      "narrative": "1.1 IP, 0 K vs. Eastern Kentucky (W). At 7.20 ERA through 5.0 innings on the season."
    },
    "bf28fa24": {
      "id": "bf28fa24",
      "name": "Will Haas",
      "fn": "Will",
      "ln": "Haas",
      "pos": "LHP",
      "yr": "Fr.",
      "num": "42",
      "school": "University of Tennessee, Knoxville",
      "season_batting": null,
      "season_pitching": {
        "era": 10.8,
        "whip": 2.4,
        "w": 0,
        "l": 0,
        "sv": 0,
        "g": 3,
        "gs": 0,
        "ip": 1.2,
        "h": 2,
        "r": 2,
        "er": 2,
        "bb": 2,
        "so": 4,
        "hr": 1,
        "hbp": 0,
        "wp": 0,
        "opp_avg": ".286"
      },
      "last_game": {
        "date": "2026-03-10",
        "opponent": "Tennessee Tech",
        "result": "W",
        "boxscore_url": "https://www.utsports.com/sports/baseball/stats/2026/tennessee-tech/boxscore/29939",
        "batting": null,
        "pitching": {
          "ip": "0.2",
          "h": 0,
          "r": 1,
          "er": 1,
          "bb": 1,
          "so": 2,
          "wp": 0,
          "hbp": 0,
          "w": 0,
          "l": 0,
          "sv": 0
        }
      },
      "narrative": "Took the mound against Tennessee Tech, throwing 0.2 innings. Allowed 1 earned run(s) with 2 strikeout(s)."
    },
    "de802ac0": {
      "id": "de802ac0",
      "name": "Nic Abraham",
      "fn": "Nic",
      "ln": "Abraham",
      "pos": "RHP",
      "yr": "So.",
      "num": "44",
      "school": "University of Tennessee, Knoxville",
      "season_batting": null,
      "season_pitching": {
        "era": 0.96,
        "whip": 0.96,
        "w": 1,
        "l": 0,
        "sv": 0,
        "g": 6,
        "gs": 0,
        "ip": 9.1,
        "h": 7,
        "r": 1,
        "er": 1,
        "bb": 2,
        "so": 5,
        "hr": 1,
        "hbp": 4,
        "wp": 0,
        "opp_avg": ".219"
      },
      "last_game": {
        "date": "2026-03-17",
        "opponent": "Eastern Kentucky",
        "result": "W",
        "boxscore_url": "https://www.utsports.com/sports/baseball/stats/2026/eastern-kentucky/boxscore/29940",
        "batting": null,
        "pitching": {
          "ip": "1.0",
          "h": 1,
          "r": 0,
          "er": 0,
          "bb": 0,
          "so": 0,
          "wp": 0,
          "hbp": 0,
          "w": 0,
          "l": 0,
          "sv": 0
        }
      },
      "narrative": "1.0 IP, 0 K vs. Eastern Kentucky (W). At 0.99 ERA through 9.1 innings on the season."
    },
    "e71691a2": {
      "id": "e71691a2",
      "name": "Jax Bishop",
      "fn": "Jax",
      "ln": "Bishop",
      "pos": "RHP",
      "yr": "Fr.",
      "num": "46",
      "school": "University of Tennessee, Knoxville",
      "season_batting": null,
      "season_pitching": {
        "era": 6.75,
        "whip": 2.25,
        "w": 0,
        "l": 0,
        "sv": 0,
        "g": 2,
        "gs": 0,
        "ip": 1.1,
        "h": 2,
        "r": 1,
        "er": 1,
        "bb": 1,
        "so": 1,
        "hr": 1,
        "hbp": 0,
        "wp": 0,
        "opp_avg": ".333"
      },
      "last_game": {
        "date": "2026-03-10",
        "opponent": "Tennessee Tech",
        "result": "W",
        "boxscore_url": "https://www.utsports.com/sports/baseball/stats/2026/tennessee-tech/boxscore/29939",
        "batting": null,
        "pitching": {
          "ip": "0.1",
          "h": 1,
          "r": 0,
          "er": 0,
          "bb": 1,
          "so": 0,
          "wp": 0,
          "hbp": 0,
          "w": 0,
          "l": 0,
          "sv": 0
        }
      },
      "narrative": "Took the mound against Tennessee Tech, throwing 0.1 innings. Allowed 0 earned run(s) with 0 strikeout(s)."
    },
    "41134fe4": {
      "id": "41134fe4",
      "name": "Chandler Day",
      "fn": "Chandler",
      "ln": "Day",
      "pos": "LHP",
      "yr": "Fr.",
      "num": "48",
      "school": "University of Tennessee, Knoxville",
      "season_batting": null,
      "season_pitching": {
        "era": 16.2,
        "whip": 3.0,
        "w": 0,
        "l": 0,
        "sv": 0,
        "g": 3,
        "gs": 0,
        "ip": 1.2,
        "h": 4,
        "r": 3,
        "er": 3,
        "bb": 1,
        "so": 1,
        "hr": 0,
        "hbp": 0,
        "wp": 1,
        "opp_avg": ".500"
      },
      "last_game": {
        "date": "2026-03-10",
        "opponent": "Tennessee Tech",
        "result": "W",
        "boxscore_url": "https://www.utsports.com/sports/baseball/stats/2026/tennessee-tech/boxscore/29939",
        "batting": null,
        "pitching": {
          "ip": "0.1",
          "h": 0,
          "r": 0,
          "er": 0,
          "bb": 0,
          "so": 0,
          "wp": 0,
          "hbp": 0,
          "w": 0,
          "l": 0,
          "sv": 0
        }
      },
      "narrative": "Took the mound against Tennessee Tech, throwing 0.1 innings. Allowed 0 earned run(s) with 0 strikeout(s)."
    }
  },
  "narratives_generated_by": "claude-haiku-4-5-20251001"
}